cli/__init__.py
cli/main.py
cli/parser.py
forgy/__init__.py
forgy/database.py
forgy/filesystem_utils.py
forgy/isbn_regex.py
forgy/logger.py
forgy/messyforg.py
forgy/metadata_search.py
forgy/process_stats.py
forgy/text_extraction.py
forgy-0.1.4.dist-info/licenses/LICENSE
forgy-0.1.4.dist-info/METADATA
forgy-0.1.4.dist-info/WHEEL
forgy-0.1.4.dist-info/entry_points.txt
forgy-0.1.4.dist-info/top_level.txt
forgy-0.1.4.dist-info/RECORD
