Metadata-Version: 2.4
Name: forgy
Version: 0.1.4
Summary: A powerful file organizer and ebook manager for e-book metadata retrieval and renaming with ease
Home-page: https://github.com/misterola/forgy
Author: Lamide I. Ogundeji
Author-email: midetobi@gmail.com
License: AGPL-3.0
Classifier: Programming Language :: Python :: 3
Classifier: License :: OSI Approved :: GNU Affero General Public License v3
Classifier: Operating System :: OS Independent
Classifier: Programming Language :: Python :: 3.10
Requires-Python: >3.10
License-File: LICENSE
Requires-Dist: pypdf==5.0.1
Requires-Dist: requests==2.32.3
Requires-Dist: reportlab==4.2.2
Requires-Dist: python-dotenv==1.1.0
Requires-Dist: flake8==7.1.1
Dynamic: author
Dynamic: author-email
Dynamic: classifier
Dynamic: description
Dynamic: description-content-type
Dynamic: home-page
Dynamic: license
Dynamic: license-file
Dynamic: requires-dist
Dynamic: requires-python
Dynamic: summary
